{"summaries":[{"symbol":{"__symbol":0,"members":[]},"metadata":{"__symbolic":"class","members":{"columns":[{"__symbolic":"property","decorators":[{"__symbolic":"call","expression":{"__symbol":1,"members":[]}}]}],"innerWidth":[{"__symbolic":"property","decorators":[{"__symbolic":"call","expression":{"__symbol":1,"members":[]}}]}],"expanded":[{"__symbolic":"property","decorators":[{"__symbolic":"call","expression":{"__symbol":1,"members":[]}}]}],"rowClass":[{"__symbolic":"property","decorators":[{"__symbolic":"call","expression":{"__symbol":1,"members":[]}}]}],"row":[{"__symbolic":"property","decorators":[{"__symbolic":"call","expression":{"__symbol":1,"members":[]}}]}],"group":[{"__symbolic":"property","decorators":[{"__symbolic":"call","expression":{"__symbol":1,"members":[]}}]}],"offsetX":[{"__symbolic":"property","decorators":[{"__symbolic":"call","expression":{"__symbol":1,"members":[]}}]}],"isSelected":[{"__symbolic":"property","decorators":[{"__symbolic":"call","expression":{"__symbol":1,"members":[]}}]}],"rowIndex":[{"__symbolic":"property","decorators":[{"__symbolic":"call","expression":{"__symbol":1,"members":[]}}]}],"cssClass":[{"__symbolic":"property","decorators":[{"__symbolic":"call","expression":{"__symbol":2,"members":[]},"arguments":["class"]}]}],"rowHeight":[{"__symbolic":"property","decorators":[{"__symbolic":"call","expression":{"__symbol":2,"members":[]},"arguments":["style.height.px"]},{"__symbolic":"call","expression":{"__symbol":1,"members":[]}}]}],"columnsTotalWidths":[{"__symbolic":"property","decorators":[{"__symbolic":"call","expression":{"__symbol":2,"members":[]},"arguments":["style.width.px"]}]}],"activate":[{"__symbolic":"property","decorators":[{"__symbolic":"call","expression":{"__symbol":3,"members":[]}}]}],"__ctor__":[{"__symbolic":"constructor","parameters":[{"__symbol":4,"members":[]},{"__symbol":5,"members":[]},{"__symbol":6,"members":[]},{"__symbol":7,"members":[]}]}],"ngDoCheck":[{"__symbolic":"method"}],"trackByGroups":[{"__symbolic":"method"}],"columnTrackingFn":[{"__symbolic":"method"}],"stylesByGroup":[{"__symbolic":"method"}],"onActivate":[{"__symbolic":"method"}],"onKeyDown":[{"__symbolic":"method","decorators":[{"__symbolic":"call","expression":{"__symbol":8,"members":[]},"arguments":["keydown",["$event"]]}]}],"onMouseenter":[{"__symbolic":"method","decorators":[{"__symbolic":"call","expression":{"__symbol":8,"members":[]},"arguments":["mouseenter",["$event"]]}]}],"recalculateColumns":[{"__symbolic":"method"}]}},"type":{"summaryKind":1,"type":{"reference":{"__symbol":0,"members":[]},"diDeps":[{"isAttribute":false,"isHost":false,"isSelf":false,"isSkipSelf":false,"isOptional":false,"token":{"identifier":{"reference":{"__symbol":4,"members":[]}}}},{"isAttribute":false,"isHost":false,"isSelf":false,"isSkipSelf":false,"isOptional":false,"token":{"identifier":{"reference":{"__symbol":9,"members":[]}}}},{"isAttribute":false,"isHost":false,"isSelf":false,"isSkipSelf":false,"isOptional":false,"token":{"identifier":{"reference":{"__symbol":6,"members":[]}}}},{"isAttribute":false,"isHost":false,"isSelf":false,"isSkipSelf":false,"isOptional":false,"token":{"identifier":{"reference":{"__symbol":7,"members":[]}}}}],"lifecycleHooks":[2]},"isComponent":true,"selector":"datatable-body-row","exportAs":null,"inputs":{"columns":"columns","innerWidth":"innerWidth","expanded":"expanded","rowClass":"rowClass","row":"row","group":"group","offsetX":"offsetX","isSelected":"isSelected","rowIndex":"rowIndex","rowHeight":"rowHeight"},"outputs":{"activate":"activate"},"hostListeners":{"keydown":"onKeyDown($event)","mouseenter":"onMouseenter($event)"},"hostProperties":{"class":"cssClass","style.height.px":"rowHeight","style.width.px":"columnsTotalWidths"},"hostAttributes":{},"providers":[],"viewProviders":[],"queries":[],"viewQueries":[],"entryComponents":[],"changeDetection":0,"template":{"ngContentSelectors":[],"encapsulation":2},"componentViewType":{"__symbol":10,"members":[]},"rendererType":{"__symbol":11,"members":[]},"componentFactory":{"__symbol":12,"members":[]}}}],"symbols":[{"__symbol":0,"name":"DataTableBodyRowComponent","filePath":"/Users/kjannis/Documents/Personal/ng-datatable/src/components/body/body-row.component.d.ts"},{"__symbol":1,"name":"Input","filePath":"/Users/kjannis/Documents/Personal/ng-datatable/node_modules/@angular/core/core.d.ts"},{"__symbol":2,"name":"HostBinding","filePath":"/Users/kjannis/Documents/Personal/ng-datatable/node_modules/@angular/core/core.d.ts"},{"__symbol":3,"name":"Output","filePath":"/Users/kjannis/Documents/Personal/ng-datatable/node_modules/@angular/core/core.d.ts"},{"__symbol":4,"name":"KeyValueDiffers","filePath":"/Users/kjannis/Documents/Personal/ng-datatable/node_modules/@angular/core/core.d.ts"},{"__symbol":5,"name":"ScrollbarHelper","filePath":"/Users/kjannis/Documents/Personal/ng-datatable/src/services/index.d.ts"},{"__symbol":6,"name":"ChangeDetectorRef","filePath":"/Users/kjannis/Documents/Personal/ng-datatable/node_modules/@angular/core/core.d.ts"},{"__symbol":7,"name":"ElementRef","filePath":"/Users/kjannis/Documents/Personal/ng-datatable/node_modules/@angular/core/core.d.ts"},{"__symbol":8,"name":"HostListener","filePath":"/Users/kjannis/Documents/Personal/ng-datatable/node_modules/@angular/core/core.d.ts"},{"__symbol":9,"name":"ScrollbarHelper","filePath":"/Users/kjannis/Documents/Personal/ng-datatable/src/services/scrollbar-helper.service.d.ts"},{"__symbol":10,"name":"View_DataTableBodyRowComponent_0","filePath":"/Users/kjannis/Documents/Personal/ng-datatable/src/components/body/body-row.component.ngfactory.d.ts"},{"__symbol":11,"name":"RenderType_DataTableBodyRowComponent","filePath":"/Users/kjannis/Documents/Personal/ng-datatable/src/components/body/body-row.component.ngfactory.d.ts"},{"__symbol":12,"name":"DataTableBodyRowComponentNgFactory","filePath":"/Users/kjannis/Documents/Personal/ng-datatable/src/components/body/body-row.component.ngfactory.d.ts"}]}