[{"__symbolic":"module","version":4,"metadata":{"NgxDatatableModule":{"__symbolic":"class","decorators":[{"__symbolic":"call","expression":{"__symbolic":"reference","module":"@angular/core","name":"NgModule","line":41,"character":1},"arguments":[{"imports":[{"__symbolic":"reference","module":"@angular/common","name":"CommonModule","line":43,"character":4}],"providers":[{"__symbolic":"reference","module":"./services","name":"ScrollbarHelper","line":46,"character":4},{"__symbolic":"reference","module":"./services","name":"DimensionsHelper","line":47,"character":4}],"declarations":[{"__symbolic":"reference","module":"./components","name":"DataTableFooterTemplateDirective","line":50,"character":4},{"__symbolic":"reference","module":"./directives","name":"VisibilityDirective","line":51,"character":4},{"__symbolic":"reference","module":"./directives","name":"DraggableDirective","line":52,"character":4},{"__symbolic":"reference","module":"./directives","name":"ResizeableDirective","line":53,"character":4},{"__symbolic":"reference","module":"./directives","name":"OrderableDirective","line":54,"character":4},{"__symbolic":"reference","module":"./directives","name":"LongPressDirective","line":55,"character":4},{"__symbolic":"reference","module":"./components","name":"ScrollerComponent","line":56,"character":4},{"__symbolic":"reference","module":"./components","name":"DatatableComponent","line":57,"character":4},{"__symbolic":"reference","module":"./components","name":"DataTableColumnDirective","line":58,"character":4},{"__symbolic":"reference","module":"./components","name":"DataTableHeaderComponent","line":59,"character":4},{"__symbolic":"reference","module":"./components","name":"DataTableHeaderCellComponent","line":60,"character":4},{"__symbolic":"reference","module":"./components","name":"DataTableBodyComponent","line":61,"character":4},{"__symbolic":"reference","module":"./components","name":"DataTableFooterComponent","line":62,"character":4},{"__symbolic":"reference","module":"./components","name":"DataTablePagerComponent","line":63,"character":4},{"__symbolic":"reference","module":"./components","name":"ProgressBarComponent","line":64,"character":4},{"__symbolic":"reference","module":"./components","name":"DataTableBodyRowComponent","line":65,"character":4},{"__symbolic":"reference","module":"./components","name":"DataTableRowWrapperComponent","line":66,"character":4},{"__symbolic":"reference","module":"./components","name":"DatatableRowDetailDirective","line":67,"character":4},{"__symbolic":"reference","module":"./components","name":"DatatableGroupHeaderDirective","line":68,"character":4},{"__symbolic":"reference","module":"./components","name":"DatatableRowDetailTemplateDirective","line":69,"character":4},{"__symbolic":"reference","module":"./components","name":"DataTableBodyCellComponent","line":70,"character":4},{"__symbolic":"reference","module":"./components","name":"DataTableSelectionComponent","line":71,"character":4},{"__symbolic":"reference","module":"./components","name":"DataTableColumnHeaderDirective","line":72,"character":4},{"__symbolic":"reference","module":"./components","name":"DataTableColumnCellDirective","line":73,"character":4},{"__symbolic":"reference","module":"./components","name":"DatatableFooterDirective","line":74,"character":4},{"__symbolic":"reference","module":"./components","name":"DatatableGroupHeaderTemplateDirective","line":75,"character":4},{"__symbolic":"reference","module":"./components","name":"DataTableSummaryRowComponent","line":76,"character":4}],"exports":[{"__symbolic":"reference","module":"./components","name":"DatatableComponent","line":79,"character":4},{"__symbolic":"reference","module":"./components","name":"DatatableRowDetailDirective","line":80,"character":4},{"__symbolic":"reference","module":"./components","name":"DatatableGroupHeaderDirective","line":81,"character":4},{"__symbolic":"reference","module":"./components","name":"DatatableRowDetailTemplateDirective","line":82,"character":4},{"__symbolic":"reference","module":"./components","name":"DataTableColumnDirective","line":83,"character":4},{"__symbolic":"reference","module":"./components","name":"DataTableColumnHeaderDirective","line":84,"character":4},{"__symbolic":"reference","module":"./components","name":"DataTableColumnCellDirective","line":85,"character":4},{"__symbolic":"reference","module":"./components","name":"DataTableFooterTemplateDirective","line":86,"character":4},{"__symbolic":"reference","module":"./components","name":"DatatableFooterDirective","line":87,"character":4},{"__symbolic":"reference","module":"./components","name":"DataTablePagerComponent","line":88,"character":4},{"__symbolic":"reference","module":"./components","name":"DatatableGroupHeaderTemplateDirective","line":89,"character":4}]}]}]}}}]